odoo9_addon_purchase_order_analytic_search-9.0.1.0.0.99.dev2-py2.7-nspkg.pth
odoo9_addon_purchase_order_analytic_search-9.0.1.0.0.99.dev2.dist-info/DESCRIPTION.rst
odoo9_addon_purchase_order_analytic_search-9.0.1.0.0.99.dev2.dist-info/METADATA
odoo9_addon_purchase_order_analytic_search-9.0.1.0.0.99.dev2.dist-info/RECORD
odoo9_addon_purchase_order_analytic_search-9.0.1.0.0.99.dev2.dist-info/WHEEL
odoo9_addon_purchase_order_analytic_search-9.0.1.0.0.99.dev2.dist-info/metadata.json
odoo9_addon_purchase_order_analytic_search-9.0.1.0.0.99.dev2.dist-info/namespace_packages.txt
odoo9_addon_purchase_order_analytic_search-9.0.1.0.0.99.dev2.dist-info/top_level.txt
odoo_addons/purchase_order_analytic_search/README.rst
odoo_addons/purchase_order_analytic_search/__init__.py
odoo_addons/purchase_order_analytic_search/__openerp__.py
odoo_addons/purchase_order_analytic_search/i18n/ca.po
odoo_addons/purchase_order_analytic_search/i18n/de.po
odoo_addons/purchase_order_analytic_search/i18n/el_GR.po
odoo_addons/purchase_order_analytic_search/i18n/es.po
odoo_addons/purchase_order_analytic_search/i18n/es_MX.po
odoo_addons/purchase_order_analytic_search/i18n/fi.po
odoo_addons/purchase_order_analytic_search/i18n/fr.po
odoo_addons/purchase_order_analytic_search/i18n/fr_FR.po
odoo_addons/purchase_order_analytic_search/i18n/gl.po
odoo_addons/purchase_order_analytic_search/i18n/hr.po
odoo_addons/purchase_order_analytic_search/i18n/hr_HR.po
odoo_addons/purchase_order_analytic_search/i18n/hu.po
odoo_addons/purchase_order_analytic_search/i18n/it.po
odoo_addons/purchase_order_analytic_search/i18n/nl.po
odoo_addons/purchase_order_analytic_search/i18n/pt.po
odoo_addons/purchase_order_analytic_search/i18n/pt_BR.po
odoo_addons/purchase_order_analytic_search/i18n/pt_PT.po
odoo_addons/purchase_order_analytic_search/i18n/ro.po
odoo_addons/purchase_order_analytic_search/i18n/sk_SK.po
odoo_addons/purchase_order_analytic_search/i18n/sl.po
odoo_addons/purchase_order_analytic_search/i18n/vi_VN.po
odoo_addons/purchase_order_analytic_search/i18n/zh_CN.po
odoo_addons/purchase_order_analytic_search/models/__init__.py
odoo_addons/purchase_order_analytic_search/models/purchase_order.py
odoo_addons/purchase_order_analytic_search/static/description/icon.png
odoo_addons/purchase_order_analytic_search/tests/__init__.py
odoo_addons/purchase_order_analytic_search/tests/test_analytic_search.py
odoo_addons/purchase_order_analytic_search/views/purchase_order_view.xml
